LICENSE
LICENSE-3RD-PARTY
MANIFEST.in
README.md
setup.py
src/peakrdl_html/__about__.py
src/peakrdl_html/__init__.py
src/peakrdl_html/__peakrdl__.py
src/peakrdl_html/exporter.py
src/peakrdl_html/search_indexer.py
src/peakrdl_html/stringify.py
src/peakrdl_html.egg-info/PKG-INFO
src/peakrdl_html.egg-info/SOURCES.txt
src/peakrdl_html.egg-info/dependency_links.txt
src/peakrdl_html.egg-info/entry_points.txt
src/peakrdl_html.egg-info/requires.txt
src/peakrdl_html.egg-info/top_level.txt
src/peakrdl_html/static/favicon.png
src/peakrdl_html/static/launcher-windows-chrome.bat
src/peakrdl_html/static/launcher-windows-edge.bat
src/peakrdl_html/static/launcher-windows-firefox.bat
src/peakrdl_html/static/.launcher_data/firefox/user.js
src/peakrdl_html/static/css/layout.css
src/peakrdl_html/static/css/normalize.css
src/peakrdl_html/static/css/theme.css
src/peakrdl_html/static/fonts/FontAwesome/fa-regular-400.eot
src/peakrdl_html/static/fonts/FontAwesome/fa-regular-400.svg
src/peakrdl_html/static/fonts/FontAwesome/fa-regular-400.ttf
src/peakrdl_html/static/fonts/FontAwesome/fa-regular-400.woff
src/peakrdl_html/static/fonts/FontAwesome/fa-regular-400.woff2
src/peakrdl_html/static/fonts/FontAwesome/fa-solid-900.eot
src/peakrdl_html/static/fonts/FontAwesome/fa-solid-900.svg
src/peakrdl_html/static/fonts/FontAwesome/fa-solid-900.ttf
src/peakrdl_html/static/fonts/FontAwesome/fa-solid-900.woff
src/peakrdl_html/static/fonts/FontAwesome/fa-solid-900.woff2
src/peakrdl_html/static/fonts/Lato/lato-bold.eot
src/peakrdl_html/static/fonts/Lato/lato-bold.ttf
src/peakrdl_html/static/fonts/Lato/lato-bold.woff
src/peakrdl_html/static/fonts/Lato/lato-bold.woff2
src/peakrdl_html/static/fonts/Lato/lato-bolditalic.eot
src/peakrdl_html/static/fonts/Lato/lato-bolditalic.ttf
src/peakrdl_html/static/fonts/Lato/lato-bolditalic.woff
src/peakrdl_html/static/fonts/Lato/lato-bolditalic.woff2
src/peakrdl_html/static/fonts/Lato/lato-italic.eot
src/peakrdl_html/static/fonts/Lato/lato-italic.ttf
src/peakrdl_html/static/fonts/Lato/lato-italic.woff
src/peakrdl_html/static/fonts/Lato/lato-italic.woff2
src/peakrdl_html/static/fonts/Lato/lato-regular.eot
src/peakrdl_html/static/fonts/Lato/lato-regular.ttf
src/peakrdl_html/static/fonts/Lato/lato-regular.woff
